lightrdf-0.4.0.dist-info/METADATA
lightrdf-0.4.0.dist-info/WHEEL
lightrdf/python_module/terms.py
lightrdf/python_module/xml.py
lightrdf/python_module/__init__.py
lightrdf/python_module/turtle.py
lightrdf/python_module/nt.py
lightrdf/python_module/utils.py
lightrdf/python_module/parse.py
lightrdf/__init__.py
lightrdf/lightrdf.cpython-311-darwin.so
lightrdf-0.4.0.dist-info/RECORD
