Metadata-Version: 2.1
Name: lightrdf
Version: 0.4.0
Summary: A fast and lightweight Python RDF parser which wraps bindings to Rust's Rio using PyO3
Home-Page: https://github.com/ozekik/lightrdf
Author: Kentaro Ozeki <32771324+ozekik@users.noreply.github.com>
Author-email: Kentaro Ozeki <32771324+ozekik@users.noreply.github.com>
License: Apache-2.0
Project-URL: Source Code, https://github.com/ozekik/lightrdf
